MANIFEST.in
README
setup.cfg
setup.py
src/django_postal.egg-info/PKG-INFO
src/django_postal.egg-info/SOURCES.txt
src/django_postal.egg-info/dependency_links.txt
src/django_postal.egg-info/requires.txt
src/django_postal.egg-info/top_level.txt
src/postal/__init__.py
src/postal/__init__.pyc
src/postal/library.py
src/postal/library.pyc
src/postal/models.py
src/postal/models.pyc
src/postal/settings.py
src/postal/settings.pyc
src/postal/urls.py
src/postal/urls.pyc
src/postal/views.py
src/postal/views.pyc
src/postal/api/__init__.py
src/postal/api/__init__.pyc
src/postal/api/handlers.py
src/postal/api/handlers.pyc
src/postal/api/urls.py
src/postal/api/urls.pyc
src/postal/forms/__init__.py
src/postal/forms/__init__.pyc
src/postal/forms/ar/__init__.py
src/postal/forms/ar/__init__.pyc
src/postal/forms/ar/forms.py
src/postal/forms/ar/forms.pyc
src/postal/forms/co/__init__.py
src/postal/forms/co/__init__.pyc
src/postal/forms/co/forms.py
src/postal/forms/co/forms.pyc
src/postal/forms/cz/__init__.py
src/postal/forms/cz/__init__.pyc
src/postal/forms/cz/forms.py
src/postal/forms/cz/forms.pyc
src/postal/forms/de/__init__.py
src/postal/forms/de/__init__.pyc
src/postal/forms/de/forms.py
src/postal/forms/de/forms.pyc
src/postal/forms/gb/__init__.py
src/postal/forms/gb/__init__.pyc
src/postal/forms/gb/forms.py
src/postal/forms/gb/forms.pyc
src/postal/forms/ie/__init__.py
src/postal/forms/ie/__init__.pyc
src/postal/forms/ie/forms.py
src/postal/forms/ie/forms.pyc
src/postal/forms/mx/__init__.py
src/postal/forms/mx/__init__.pyc
src/postal/forms/mx/forms.py
src/postal/forms/mx/forms.pyc
src/postal/forms/nl/__init__.py
src/postal/forms/nl/__init__.pyc
src/postal/forms/nl/forms.py
src/postal/forms/nl/forms.pyc
src/postal/forms/pl/__init__.py
src/postal/forms/pl/__init__.pyc
src/postal/forms/pl/forms.py
src/postal/forms/pl/forms.pyc
src/postal/forms/ru/__init__.py
src/postal/forms/ru/__init__.pyc
src/postal/forms/ru/forms.py
src/postal/forms/ru/forms.pyc
src/postal/forms/us/__init__.py
src/postal/forms/us/__init__.pyc
src/postal/forms/us/forms.py
src/postal/forms/us/forms.pyc
src/postal/templates/postal/form.html
src/postal/templates/postal/monitor_country_change.html
