Metadata-Version: 1.1
Name: django-postal
Version: 0.95
Summary: A Django app for l10n of postal addresses.
Home-page: http://github.com/mthornhill/django-postal
Author: Michael Thornhill
Author-email: michael@maithu.com
License: BSD
Platform: UNKNOWN
Classifier: Development Status :: 3 - Alpha
Classifier: Framework :: Django
Classifier: Intended Audience :: Developers
Classifier: License :: OSI Approved :: BSD License
Classifier: Operating System :: OS Independent
Classifier: Programming Language :: Python
Classifier: Topic :: Internet :: WWW/HTTP
